[
  {
    "_id": { "$oid": "69f8a1b2c3d4e5f6a7b8c920" },
    "bookingId": { "$oid": "66f8a1b2c3d4e5f6a7b8c9f0" },
    "payerId": { "$oid": "64f8a1b2c3d4e5f6a7b8c9d1" },
    "receiverId": { "$oid": "64f8a1b2c3d4e5f6a7b8c9d0" },
    "amount": 150,
    "currency": "INR",
    "paymentMethod": "digital_wallet",
    "transactionId": "TXN_001",
    "status": "completed",
    "paymentGateway": "DummyPay",
    "gatewayTransactionId": "dummy_txn_001",
    "refundAmount": 0,
    "refundReason": null,
    "processedAt": { "$date": "2025-07-22T16:50:00Z" },
    "createdAt": { "$date": "2025-07-22T16:45:00Z" }
  },
  {
    "_id": { "$oid": "69f8a1b2c3d4e5f6a7b8c921" },
    "bookingId": { "$oid": "66f8a1b2c3d4e5f6a7b8c9f1" },
    "payerId": { "$oid": "64f8a1b2c3d4e5f6a7b8c9d5" },
    "receiverId": { "$oid": "64f8a1b2c3d4e5f6a7b8c9d4" },
    "amount": 120,
    "currency": "INR",
    "paymentMethod": "credit_card",
    "transactionId": "TXN_002",
    "status": "completed",
    "paymentGateway": "MockPay",
    "gatewayTransactionId": "mock_txn_002",
    "refundAmount": 0,
    "refundReason": null,
    "processedAt": { "$date": "2025-07-21T13:15:00Z" },
    "createdAt": { "$date": "2025-07-21T13:10:00Z" }
  },
  {
    "_id": { "$oid": "69f8a1b2c3d4e5f6a7b8c922" },
    "bookingId": { "$oid": "66f8a1b2c3d4e5f6a7b8c9f3" },
    "payerId": { "$oid": "64f8a1b2c3d4e5f6a7b8c9d1" },
    "receiverId": { "$oid": "64f8a1b2c3d4e5f6a7b8c9d9" },
    "amount": 120,
    "currency": "INR",
    "paymentMethod": "digital_wallet",
    "transactionId": "TXN_003",
    "status": "completed",
    "paymentGateway": "TestPay",
    "gatewayTransactionId": "test_txn_003",
    "refundAmount": 0,
    "refundReason": null,
    "processedAt": { "$date": "2025-07-23T17:35:00Z" },
    "createdAt": { "$date": "2025-07-23T17:30:00Z" }
  },
  {
    "_id": { "$oid": "69f8a1b2c3d4e5f6a7b8c923" },
    "bookingId": { "$oid": "66f8a1b2c3d4e5f6a7b8c9f5" },
    "payerId": { "$oid": "64f8a1b2c3d4e5f6a7b8c9d1" },
    "receiverId": { "$oid": "64f8a1b2c3d4e5f6a7b8c9d4" },
    "amount": 50,
    "currency": "INR",
    "paymentMethod": "upi",
    "transactionId": "TXN_004",
    "status": "completed",
    "paymentGateway": "DummyUPI",
    "gatewayTransactionId": "upi_dummy_004",
    "refundAmount": 0,
    "refundReason": null,
    "processedAt": { "$date": "2025-07-23T19:25:00Z" },
    "createdAt": { "$date": "2025-07-23T19:20:00Z" }
  },
  {
    "_id": { "$oid": "69f8a1b2c3d4e5f6a7b8c924" },
    "bookingId": { "$oid": "66f8a1b2c3d4e5f6a7b8c9f6" },
    "payerId": { "$oid": "64f8a1b2c3d4e5f6a7b8c9d7" },
    "receiverId": { "$oid": "64f8a1b2c3d4e5f6a7b8c9d2" },
    "amount": 320,
    "currency": "INR",
    "paymentMethod": "credit_card",
    "transactionId": "TXN_005",
    "status": "completed",
    "paymentGateway": "MockPay",
    "gatewayTransactionId": "mock_txn_005",
    "refundAmount": 0,
    "refundReason": null,
    "processedAt": { "$date": "2025-07-18T15:20:00Z" },
    "createdAt": { "$date": "2025-07-18T15:15:00Z" }
  },
  {
    "_id": { "$oid": "69f8a1b2c3d4e5f6a7b8c925" },
    "bookingId": { "$oid": "66f8a1b2c3d4e5f6a7b8c9f7" },
    "payerId": { "$oid": "64f8a1b2c3d4e5f6a7b8c9d1" },
    "receiverId": { "$oid": "64f8a1b2c3d4e5f6a7b8c9d6" },
    "amount": 100,
    "currency": "INR",
    "paymentMethod": "digital_wallet",
    "transactionId": "TXN_006",
    "status": "refunded",
    "paymentGateway": "DummyPay",
    "gatewayTransactionId": "dummy_txn_006",
    "refundAmount": 100,
    "refundReason": "Driver cancelled - car breakdown",
    "processedAt": { "$date": "2025-07-23T12:35:00Z" },
    "createdAt": { "$date": "2025-07-23T12:30:00Z" }
  },
  {
    "_id": { "$oid": "69f8a1b2c3d4e5f6a7b8c926" },
    "bookingId": { "$oid": "66f8a1b2c3d4e5f6a7b8c9f2" },
    "payerId": { "$oid": "64f8a1b2c3d4e5f6a7b8c9d7" },
    "receiverId": { "$oid": "64f8a1b2c3d4e5f6a7b8c9d4" },
    "amount": 120,
    "currency": "INR",
    "paymentMethod": "credit_card",
    "transactionId": "TXN_007",
    "status": "pending",
    "paymentGateway": "TestPay",
    "gatewayTransactionId": "test_pending_007",
    "refundAmount": 0,
    "refundReason": null,
    "processedAt": null,
    "createdAt": { "$date": "2025-07-22T10:35:00Z" }
  },
  {
    "_id": { "$oid": "69f8a1b2c3d4e5f6a7b8c927" },
    "bookingId": { "$oid": "66f8a1b2c3d4e5f6a7b8c9f4" },
    "payerId": { "$oid": "64f8a1b2c3d4e5f6a7b8c9d5" },
    "receiverId": { "$oid": "64f8a1b2c3d4e5f6a7b8c9d3" },
    "amount": 70,
    "currency": "INR",
    "paymentMethod": "digital_wallet",
    "transactionId": "TXN_008",
    "status": "pending",
    "paymentGateway": "DummyPay",
    "gatewayTransactionId": "dummy_pending_008",
    "refundAmount": 0,
    "refundReason": null,
    "processedAt": null,
    "createdAt": { "$date": "2025-07-23T14:25:00Z" }
  },
  {
    "_id": { "$oid": "69f8a1b2c3d4e5f6a7b8c928" },
    "bookingId": { "$oid": "66f8a1b2c3d4e5f6a7b8c9f8" },
    "payerId": { "$oid": "64f8a1b2c3d4e5f6a7b8c9d5" },
    "receiverId": { "$oid": "64f8a1b2c3d4e5f6a7b8c9d2" },
    "amount": 80,
    "currency": "INR",
    "paymentMethod": "upi",
    "transactionId": "TXN_009",
    "status": "pending",
    "paymentGateway": "DummyUPI",
    "gatewayTransactionId": "upi_pending_009",
    "refundAmount": 0,
    "refundReason": null,
    "processedAt": null,
    "createdAt": { "$date": "2025-07-23T20:40:00Z" }
  },
  {
    "_id": { "$oid": "69f8a1b2c3d4e5f6a7b8c929" },
    "bookingId": { "$oid": "66f8a1b2c3d4e5f6a7b8c9f9" },
    "payerId": { "$oid": "64f8a1b2c3d4e5f6a7b8c9d7" },
    "receiverId": { "$oid": "64f8a1b2c3d4e5f6a7b8c9d0" },
    "amount": 200,
    "currency": "INR",
    "paymentMethod": "credit_card",
    "transactionId": "TXN_010",
    "status": "failed",
    "paymentGateway": "MockPay",
    "gatewayTransactionId": "mock_failed_010",
    "refundAmount": 0,
    "refundReason": "Insufficient funds",
    "processedAt": null,
    "createdAt": { "$date": "2025-07-23T21:20:00Z" }
  }
]